linuxsysstat.py
linuxsysstat-0.1.2.dist-info/METADATA
linuxsysstat-0.1.2.dist-info/WHEEL
linuxsysstat-0.1.2.dist-info/entry_points.txt
linuxsysstat-0.1.2.dist-info/RECORD
